{
    "data": [
        {
            "tags": [],
            "posted_date": "2020-04-16T13:01:42.933000",
            "name": "Page 1",
            "_id": "2020-04-16T13:01:42.933000-31c591b1-e144-496e-b672-2b7ba3c8b1eb",
            "content": [
                {
                    "type": "text",
                    "title": "This is a thought I just had about this"
                },
                {
                    "type": "text",
                    "title": ""
                }
            ]
        },
        {
            "tags": [],
            "posted_date": "2020-04-16T13:01:42.933000",
            "name": "Page 2",
            "_id": "2020-04-16T13:01:42.933000-456fb914-c4d7-45b8-9cec-ea164447742f",
            "content": [
                {
                    "type": "text",
                    "title": "This is another thought"
                }
            ]
        },
        {
            "tags": [],
            "posted_date": "2020-04-16T13:01:42.933000",
            "name": "Page 3",
            "_id": "2020-04-16T13:01:42.933000-972f552a-a0c7-42e5-a653-0f467aceeeea",
            "content": [
                {
                    "type": "text",
                    "title": "So many thoughts!"
                }
            ]
        }
    ]
}